<?xml version = '1.0' encoding = 'UTF-8'?>
<TableProxyOraclev12c class="oracle.dbtools.crest.model.design.storage.oracle.v12c.TableProxyOraclev12c" name="state_dim" directorySegmentName="seg_0" id="984DD6A9-A5B0-EA9D-56EF-A8AE099CA19B">
<createdBy>beng</createdBy>
<createdTime>2016-07-18 13:11:10 UTC</createdTime>
<ownerDesignName>VoterModel</ownerDesignName>
<partitionedRowMovement>DISABLE</partitionedRowMovement>
<temporaryChanged>false</temporaryChanged>
<accessDriverType>oracle_loader</accessDriverType>
<rejectLimit></rejectLimit>
<primaryKeys>
<PrimaryKey class="oracle.dbtools.crest.model.design.storage.oracle.v10g.PKProxyOraclev10g" name="IFv8_PK" id="5FF62A4E-93A3-2D7B-95EB-5F5627973213">
<createdBy>beng</createdBy>
<createdTime>2016-07-18 13:11:10 UTC</createdTime>
<ownerDesignName>VoterModel</ownerDesignName>
<indexSort>SORTED</indexSort>
</PrimaryKey>
</primaryKeys>
</TableProxyOraclev12c>