<?xml version = '1.0' encoding = 'UTF-8'?>
<Diagram class="oracle.dbtools.crest.swingui.logical.DPVLogicalSubView" name="Canvassing Model" id="9FFF1664-ACE6-2274-7E4B-9CDCA6E4FB7F">
<createdBy>beng</createdBy>
<modifiedBy>beng</modifiedBy>
<createdTime>2016-07-18 20:07:59 UTC</createdTime>
<autoRoute>false</autoRoute>
<boxInbox>true</boxInbox>
<showLegend>false</showLegend>
<showLabels>false</showLabels>
<showRelAttributes>false</showRelAttributes>
<gridEnabled>false</gridEnabled>
<showGrid>false</showGrid>
<diagramColor>-1</diagramColor>
<display>false</display>
<notation>1</notation>
<objectViews>
<OView class="oracle.dbtools.crest.swingui.logical.TVEntity" oid="094B9AC0-02AC-2A82-CE79-8581FDCEA4E9" otype="Entity" vid="60567319-4002-CD62-75F0-3F1FCC9FEE62">
<hideElementsInCurrentOnly>false</hideElementsInCurrentOnly>
<bounds x="88" y="386" width="191" height="404"/>
</OView>
<OView class="oracle.dbtools.crest.swingui.logical.TVEntity" oid="214B6914-4C2D-56B7-2B80-6EB199C43FB4" otype="Entity" vid="2E20DBEA-60FF-0C7C-AF3B-FDC8F3389845">
<hideElementsInCurrentOnly>false</hideElementsInCurrentOnly>
<bounds x="623" y="688" width="178" height="82"/>
</OView>
<OView class="oracle.dbtools.crest.swingui.logical.TVEntity" oid="2BB738BB-5A88-475E-187B-A6FBB2E39750" otype="Entity" vid="581AC645-0645-C41F-9E8D-6A2DAAAA18C5">
<hideElementsInCurrentOnly>false</hideElementsInCurrentOnly>
<bounds x="1379" y="679" width="115" height="96"/>
</OView>
<OView class="oracle.dbtools.crest.swingui.logical.TVEntity" oid="2DB6FF76-F47B-51B8-B115-8277F4FB42EB" otype="Entity" vid="967DA5D9-649F-B5D2-6351-5E6F346C8F5F">
<hideElementsInCurrentOnly>false</hideElementsInCurrentOnly>
<bounds x="945" y="21" width="128" height="180"/>
</OView>
<OView class="oracle.dbtools.crest.swingui.logical.TVEntity" oid="4E95D912-3E38-A1D2-97EB-3D9BC83DEE98" otype="Entity" vid="E922D0A9-0172-38E9-3179-128CEFC5EAC8">
<hideElementsInCurrentOnly>false</hideElementsInCurrentOnly>
<bounds x="327" y="28" width="107" height="82"/>
</OView>
<OView class="oracle.dbtools.crest.swingui.logical.TVEntity" oid="7756C07B-BA2B-489B-8686-3871B2D46A99" otype="Entity" vid="181CE93F-93D1-B375-D1E5-50634EEDAF47">
<hideElementsInCurrentOnly>false</hideElementsInCurrentOnly>
<bounds x="1420" y="291" width="162" height="82"/>
</OView>
<OView class="oracle.dbtools.crest.swingui.logical.TVEntity" oid="796C782D-8E01-DD0E-C8A9-6B85B2F43CAC" otype="Entity" vid="2F03BF6B-924D-DADF-4EF8-A0991D3CB66F">
<hideElementsInCurrentOnly>false</hideElementsInCurrentOnly>
<bounds x="1231" y="198" width="170" height="110"/>
</OView>
<OView class="oracle.dbtools.crest.swingui.logical.TVEntity" oid="9AF79FF2-0CA0-05C8-856F-839110FC7A16" otype="Entity" vid="A4612340-ADE3-3E98-BFA0-A7AA9C13C74A">
<hideElementsInCurrentOnly>false</hideElementsInCurrentOnly>
<bounds x="734" y="142" width="129" height="68"/>
</OView>
<OView class="oracle.dbtools.crest.swingui.logical.TVEntity" oid="ACDD50C5-AF86-9D90-2844-25D3490C032D" otype="Entity" vid="D7F38BFF-1E51-323F-8DCF-DF3623377913">
<hideElementsInCurrentOnly>false</hideElementsInCurrentOnly>
<bounds x="538" y="65" width="169" height="54"/>
</OView>
<OView class="oracle.dbtools.crest.swingui.logical.TVEntity" oid="AD99DDC2-841B-6B3C-9382-8DF3A134B7B5" otype="Entity" vid="48B09DC3-B1DC-1E7B-793B-FFC69D2F2328">
<hideElementsInCurrentOnly>false</hideElementsInCurrentOnly>
<bounds x="93" y="138" width="240" height="194"/>
</OView>
<OView class="oracle.dbtools.crest.swingui.logical.TVEntity" oid="CDF9EF95-EFB7-9E8B-F4C4-B535E56B40CE" otype="Entity" vid="E6B99786-213B-D94B-46F1-3489CDB324D2">
<hideElementsInCurrentOnly>false</hideElementsInCurrentOnly>
<bounds x="1469" y="539" width="174" height="124"/>
</OView>
<OView class="oracle.dbtools.crest.swingui.logical.TVEntity" oid="D6296548-B8A7-F1C8-EB53-3BC5AF310373" otype="Entity" vid="CFC8A42C-6FCC-48F4-CD97-3B73EE5E70F0">
<hideElementsInCurrentOnly>false</hideElementsInCurrentOnly>
<bounds x="351" y="560" width="147" height="264"/>
</OView>
<OView class="oracle.dbtools.crest.swingui.logical.TVEntity" oid="EE1CD861-006B-1B39-025E-0110531B1052" otype="Entity" vid="C3053C8F-537D-61A8-33A3-A06FA66A3513">
<hideElementsInCurrentOnly>false</hideElementsInCurrentOnly>
<bounds x="1423" y="400" width="165" height="82"/>
</OView>
<OView class="oracle.dbtools.crest.swingui.logical.TVEntity" oid="F016C040-96E6-3177-EF91-1E47724A65F0" otype="Entity" vid="00CB7476-F615-332B-AC8A-35E9BB690C64">
<hideElementsInCurrentOnly>false</hideElementsInCurrentOnly>
<bounds x="628" y="863" width="106" height="54"/>
</OView>
<OView class="oracle.dbtools.crest.swingui.logical.TVEntity" oid="FF4FCD47-F3EA-0185-6A21-6BB4C60FA50B" otype="Entity" vid="DBDB8A9E-7A0F-162B-A65B-106A1E3E728C">
<hideElementsInCurrentOnly>false</hideElementsInCurrentOnly>
<bounds x="748" y="340" width="174" height="110"/>
</OView>
</objectViews>
<connectors>
<Connector class="oracle.dbtools.crest.swingui.logical.TVRelation" oid="073D787E-2655-A63C-3BE4-AF37152334E5" otype="Relation" vid_source="E922D0A9-0172-38E9-3179-128CEFC5EAC8" vid_target="DBDB8A9E-7A0F-162B-A65B-106A1E3E728C">
<hideElementsInCurrentOnly>false</hideElementsInCurrentOnly>
<lineWidth>1</lineWidth>
<points>
<point x="434" y="69"/>
<point x="748" y="371"/>
</points>
</Connector>
<Connector class="oracle.dbtools.crest.swingui.logical.TVRelation" oid="17321C39-1CBE-1A2C-8B35-B64C0178185F" otype="Relation" vid_source="00CB7476-F615-332B-AC8A-35E9BB690C64" vid_target="2E20DBEA-60FF-0C7C-AF3B-FDC8F3389845">
<hideElementsInCurrentOnly>false</hideElementsInCurrentOnly>
<lineWidth>1</lineWidth>
<points>
<point x="688" y="863"/>
<point x="688" y="795"/>
<point x="719" y="795"/>
<point x="719" y="770"/>
</points>
</Connector>
<Connector class="oracle.dbtools.crest.swingui.logical.TVRelation" oid="1908C337-C808-EB83-EE7F-954D46555A9C" otype="Relation" vid_source="48B09DC3-B1DC-1E7B-793B-FFC69D2F2328" vid_target="DBDB8A9E-7A0F-162B-A65B-106A1E3E728C">
<hideElementsInCurrentOnly>false</hideElementsInCurrentOnly>
<lineWidth>1</lineWidth>
<points>
<point x="333" y="235"/>
<point x="748" y="395"/>
</points>
</Connector>
<Connector class="oracle.dbtools.crest.swingui.logical.TVRelation" oid="1E3EF197-7800-DE54-2A97-C06C173F7AD6" otype="Relation" vid_source="967DA5D9-649F-B5D2-6351-5E6F346C8F5F" vid_target="DBDB8A9E-7A0F-162B-A65B-106A1E3E728C">
<hideElementsInCurrentOnly>false</hideElementsInCurrentOnly>
<lineWidth>1</lineWidth>
<points>
<point x="1023" y="201"/>
<point x="1023" y="283"/>
<point x="818" y="283"/>
<point x="818" y="340"/>
</points>
</Connector>
<Connector class="oracle.dbtools.crest.swingui.logical.TVRelation" oid="235B7AEA-ECB6-7CE2-B799-6C955F896567" otype="Relation" vid_source="D7F38BFF-1E51-323F-8DCF-DF3623377913" vid_target="DBDB8A9E-7A0F-162B-A65B-106A1E3E728C">
<hideElementsInCurrentOnly>false</hideElementsInCurrentOnly>
<lineWidth>1</lineWidth>
<points>
<point x="660" y="65"/>
<point x="660" y="99"/>
<point x="748" y="340"/>
</points>
</Connector>
<Connector class="oracle.dbtools.crest.swingui.logical.TVRelation" oid="30ADD423-910E-D2B7-29DD-9CCFC5347079" otype="Relation" vid_source="A4612340-ADE3-3E98-BFA0-A7AA9C13C74A" vid_target="DBDB8A9E-7A0F-162B-A65B-106A1E3E728C">
<hideElementsInCurrentOnly>false</hideElementsInCurrentOnly>
<lineWidth>1</lineWidth>
<points>
<point x="805" y="210"/>
<point x="805" y="340"/>
</points>
</Connector>
<Connector class="oracle.dbtools.crest.swingui.logical.TVRelation" oid="361BFB81-5776-8DBB-45F0-519EE3EA438C" otype="Relation" vid_source="2E20DBEA-60FF-0C7C-AF3B-FDC8F3389845" vid_target="DBDB8A9E-7A0F-162B-A65B-106A1E3E728C">
<hideElementsInCurrentOnly>false</hideElementsInCurrentOnly>
<lineWidth>1</lineWidth>
<points>
<point x="774" y="688"/>
<point x="837" y="450"/>
</points>
</Connector>
<Connector class="oracle.dbtools.crest.swingui.logical.TVRelation" oid="5387A0A5-3AB4-FFE2-4318-4376A1772A5D" otype="Relation" vid_source="00CB7476-F615-332B-AC8A-35E9BB690C64" vid_target="CFC8A42C-6FCC-48F4-CD97-3B73EE5E70F0">
<hideElementsInCurrentOnly>false</hideElementsInCurrentOnly>
<lineWidth>1</lineWidth>
<points>
<point x="628" y="883"/>
<point x="571" y="883"/>
<point x="571" y="759"/>
<point x="498" y="759"/>
</points>
</Connector>
<Connector class="oracle.dbtools.crest.swingui.logical.TVRelation" oid="5B0457DB-F157-904A-991E-12AA2528FDEE" otype="Relation" vid_source="181CE93F-93D1-B375-D1E5-50634EEDAF47" vid_target="DBDB8A9E-7A0F-162B-A65B-106A1E3E728C">
<hideElementsInCurrentOnly>false</hideElementsInCurrentOnly>
<lineWidth>1</lineWidth>
<points>
<point x="1420" y="356"/>
<point x="922" y="356"/>
</points>
</Connector>
<Connector class="oracle.dbtools.crest.swingui.logical.TVRelation" oid="7A24C770-135F-0DD9-C602-3A61625ECE1F" otype="Relation" vid_source="E6B99786-213B-D94B-46F1-3489CDB324D2" vid_target="DBDB8A9E-7A0F-162B-A65B-106A1E3E728C">
<hideElementsInCurrentOnly>false</hideElementsInCurrentOnly>
<lineWidth>1</lineWidth>
<points>
<point x="1469" y="601"/>
<point x="922" y="439"/>
</points>
</Connector>
<Connector class="oracle.dbtools.crest.swingui.logical.TVRelation" oid="7B9DE9E2-9419-FBF8-BF5D-C369532667DA" otype="Relation" vid_source="2F03BF6B-924D-DADF-4EF8-A0991D3CB66F" vid_target="DBDB8A9E-7A0F-162B-A65B-106A1E3E728C">
<hideElementsInCurrentOnly>false</hideElementsInCurrentOnly>
<lineWidth>1</lineWidth>
<points>
<point x="1231" y="253"/>
<point x="908" y="340"/>
</points>
</Connector>
<Connector class="oracle.dbtools.crest.swingui.logical.TVRelation" oid="8A1E4C08-7268-540A-F14B-3746270DD3D8" otype="Relation" vid_source="581AC645-0645-C41F-9E8D-6A2DAAAA18C5" vid_target="DBDB8A9E-7A0F-162B-A65B-106A1E3E728C">
<hideElementsInCurrentOnly>false</hideElementsInCurrentOnly>
<lineWidth>1</lineWidth>
<points>
<point x="1379" y="727"/>
<point x="887" y="450"/>
</points>
</Connector>
<Connector class="oracle.dbtools.crest.swingui.logical.TVRelation" oid="928C6D8A-AC76-1350-CC4A-239E9B3CA103" otype="Relation" vid_source="C3053C8F-537D-61A8-33A3-A06FA66A3513" vid_target="DBDB8A9E-7A0F-162B-A65B-106A1E3E728C">
<hideElementsInCurrentOnly>false</hideElementsInCurrentOnly>
<lineWidth>1</lineWidth>
<points>
<point x="1423" y="425"/>
<point x="922" y="403"/>
</points>
</Connector>
<Connector class="oracle.dbtools.crest.swingui.logical.TVRelation" oid="C0E2BF28-B5CE-357A-54C9-DB4440F82712" otype="Relation" vid_source="CFC8A42C-6FCC-48F4-CD97-3B73EE5E70F0" vid_target="DBDB8A9E-7A0F-162B-A65B-106A1E3E728C">
<hideElementsInCurrentOnly>false</hideElementsInCurrentOnly>
<lineWidth>1</lineWidth>
<points>
<point x="498" y="692"/>
<point x="758" y="450"/>
</points>
</Connector>
<Connector class="oracle.dbtools.crest.swingui.logical.TVRelation" oid="E8252D88-91F2-436F-CEB2-F93FDA07E765" otype="Relation" vid_source="60567319-4002-CD62-75F0-3F1FCC9FEE62" vid_target="DBDB8A9E-7A0F-162B-A65B-106A1E3E728C">
<hideElementsInCurrentOnly>false</hideElementsInCurrentOnly>
<lineWidth>1</lineWidth>
<points>
<point x="279" y="418"/>
<point x="748" y="418"/>
</points>
</Connector>
</connectors>
</Diagram>